jotdx/__init__.py
jotdx/__main__.py
jotdx/affair.py
jotdx/base_socket_client.py
jotdx/bin/__init__.py
jotdx/bin/get_tdx_trader_server.py
jotdx/bin/hqbenchmark.py
jotdx/bin/hqget.py
jotdx/bin/hqreader.py
jotdx/block.py
jotdx/config.py
jotdx/config_pytdx/__init__.py
jotdx/config_pytdx/hosts.py
jotdx/consts.py
jotdx/contrib/__init__.py
jotdx/contrib/adjust.py
jotdx/contrib/compat.py
jotdx/contrib/customize.py
jotdx/contrib/fuquan.py
jotdx/crawler/__init__.py
jotdx/crawler/base_crawler.py
jotdx/crawler/history_financial_crawler.py
jotdx/errors.py
jotdx/examples/ext_bars.py
jotdx/examples/ext_bars_range.py
jotdx/examples/ext_instrument_count.py
jotdx/examples/ext_instrument_quote_list.py
jotdx/examples/ext_instruments.py
jotdx/examples/ext_markets.py
jotdx/examples/reader.py
jotdx/examples/std_bars.py
jotdx/examples/std_index_bars.py
jotdx/examples/std_k_bar.py
jotdx/examples/std_security_count.py
jotdx/examples/std_security_list.py
jotdx/examples/std_security_quotes.py
jotdx/examples/std_transaction.py
jotdx/examples/std_xdxr_info.py
jotdx/exhq.py
jotdx/financial/__init__.py
jotdx/financial/base.py
jotdx/financial/columns.py
jotdx/financial/financial.py
jotdx/heartbeat.py
jotdx/helper.py
jotdx/hq.py
jotdx/log.py
jotdx/logger.py
jotdx/params.py
jotdx/parser/__init__.py
jotdx/parser/base.py
jotdx/parser/ex_get_history_instrument_bars_range.py
jotdx/parser/ex_get_history_minute_time_data.py
jotdx/parser/ex_get_history_transaction_data.py
jotdx/parser/ex_get_instrument_bars.py
jotdx/parser/ex_get_instrument_count.py
jotdx/parser/ex_get_instrument_info.py
jotdx/parser/ex_get_instrument_quote.py
jotdx/parser/ex_get_instrument_quote_list.py
jotdx/parser/ex_get_markets.py
jotdx/parser/ex_get_minute_time_data.py
jotdx/parser/ex_get_transaction_data.py
jotdx/parser/ex_setup_commands.py
jotdx/parser/gateway.py
jotdx/parser/get_block_info.py
jotdx/parser/get_company_info_category.py
jotdx/parser/get_company_info_content.py
jotdx/parser/get_finance_info.py
jotdx-0.1.16.dist-info/LICENSE
jotdx-0.1.16.dist-info/WHEEL
jotdx-0.1.16.dist-info/METADATA
jotdx-0.1.16.dist-info/RECORD
