Metadata-Version: 2.1
Name: jotdx
Version: 0.1.16
Summary: Get data
License: MIT
Author: FangyangJz
Author-email: fangyang.jing@hotmail.com
Requires-Python: >=3.7.1,<4.0.0
Classifier: License :: OSI Approved :: MIT License
Classifier: Programming Language :: Python :: 3
Classifier: Programming Language :: Python :: 3.10
Classifier: Programming Language :: Python :: 3.8
Classifier: Programming Language :: Python :: 3.9
Requires-Dist: click (>=8.0.3,<9.0.0)
Requires-Dist: httpx (>=0.20.0,<0.21.0)
Requires-Dist: joconst (>=0.1.14,<0.2.0)
Requires-Dist: loguru (>=0.5.3,<0.6.0)
Requires-Dist: numpy (>=1.21,<2.0)
Requires-Dist: pandas (>=1.3.4,<2.0.0)
Requires-Dist: prettytable (>=2.2.1,<3.0.0)
Requires-Dist: py-mini-racer (>=0.6.0,<0.7.0)
Requires-Dist: simplejson (>=3.17.6,<4.0.0)
Requires-Dist: tenacity (>=8.0.1,<9.0.0)
Requires-Dist: tqdm (>=4.62.3,<5.0.0)
